push_tool/__init__.py
push_tool/email.py
push_tool/utils.py
push_tool/wechat.py
tests/__init__.py
tests/test_email.py
tests/test_example.py
tests/test_utils.py
tests/test_wechat.py
push_tool_ljp-0.1.0.dist-info/LICENSE
push_tool_ljp-0.1.0.dist-info/METADATA
push_tool_ljp-0.1.0.dist-info/WHEEL
push_tool_ljp-0.1.0.dist-info/top_level.txt
push_tool_ljp-0.1.0.dist-info/RECORD
