Metadata-Version: 2.1
Name: push-tool-ljp
Version: 0.1.0
Summary: A utility for sending messages via WeChat Work bot and email
Home-page: https://github.com/yourusername/push-tool
Author: Your Name
Author-email: your.email@example.com
Classifier: Programming Language :: Python :: 3
Classifier: License :: OSI Approved :: MIT License
Classifier: Operating System :: OS Independent
Requires-Python: >=3.6
License-File: LICENSE
Requires-Dist: requests>=2.25.1
Requires-Dist: python-dotenv>=0.15.0
Provides-Extra: dev
Requires-Dist: pytest>=6.2.2; extra == "dev"
Requires-Dist: pytest-cov>=2.11.1; extra == "dev"
